hbb/__init__.py
hbb/paths/hydra.py
hbb-0.0.1.dist-info/licenses/LICENSE
hbb-0.0.1.dist-info/METADATA
hbb-0.0.1.dist-info/WHEEL
hbb-0.0.1.dist-info/top_level.txt
hbb-0.0.1.dist-info/RECORD
