Metadata-Version: 2.4
Name: hbb
Version: 0.0.1
Summary: Utility package
Author-email: Hussam Habib <hussamh10+pypi@gmail.com>
License-Expression: MIT
Classifier: Programming Language :: Python :: 3
Classifier: Operating System :: OS Independent
Requires-Python: >=3.0
License-File: LICENSE
Dynamic: license-file
